{"P2": {"labels": ["\u561a\u4e0d\u561a\u513f"], "postTitle": "\u79bb #1", "postUrl": "post/li-%20%231.html", "createdDate": "2024-08-09", "dateLabelColor": "#bc4c00"}, "P1": {"labels": ["\u561a\u4e0d\u561a\u513f"], "postTitle": "\u98ce\u5439\u82b1\u9999\u6f2b", "postUrl": "post/feng-chui-hua-xiang-man.html", "createdDate": "2024-08-09", "dateLabelColor": "#bc4c00"}, "labelColorDict": {"bug": "#d73a4a", "documentation": "#0075ca", "duplicate": "#cfd3d7", "enhancement": "#a2eeef", "good first issue": "#7057ff", "help wanted": "#008672", "invalid": "#e4e669", "question": "#d876e3", "wontfix": "#ffffff", "\u561a\u4e0d\u561a\u513f": "#A51E8C"}}